Metadata-Version: 2.1
Name: vector-shortcuts
Version: 0.2.1
Summary: Vector and linear algebra toolbelt for NumPy
Home-page: https://github.com/metabolize/vx
Author: Body Labs, Metabolize, and other contributors
Author-email: github@paulmelnikow.com
License: UNKNOWN
Project-URL: Issue Tracker, https://github.com/metabolize/vx/issues
Project-URL: Documentation, https://vx.readthedocs.io/en/stable/
Platform: UNKNOWN
Classifier: Development Status :: 4 - Beta
Classifier: Intended Audience :: Developers
Classifier: Intended Audience :: Science/Research
Classifier: Intended Audience :: Manufacturing
Classifier: Topic :: Artistic Software
Classifier: Topic :: Multimedia :: Graphics :: 3D Modeling
Classifier: Topic :: Scientific/Engineering :: Mathematics
Classifier: Topic :: Scientific/Engineering :: Visualization
Classifier: License :: OSI Approved :: BSD License
Classifier: Operating System :: OS Independent
Classifier: Programming Language :: Python :: 2.7
Classifier: Programming Language :: Python :: 3
